harley-0.1.0.dist-info/METADATA
harley-0.1.0.dist-info/WHEEL
harley-0.1.0.dist-info/licenses/LICENSE
harley/dataframe_helper.py
harley/dataframe_validator.py
harley/schema_helpers.py
harley/transformations.py
harley/to_boolean.py
harley/string_functions.py
harley/__init__.py
harley/column_functions.py
harley/utils.py
harley/maths.py
harley/harley.abi3.so
harley-0.1.0.dist-info/RECORD
